slidex/__init__.py
slidex/__init__.pyi
slidex/_core.cpython-39-darwin.so
slidex-0.1.1.dist-info/METADATA
slidex-0.1.1.dist-info/WHEEL
slidex-0.1.1.dist-info/licenses/LICENSE
slidex-0.1.1.dist-info/RECORD
