Metadata-Version: 2.4
Name: slidex
Version: 0.1.1
Classifier: Programming Language :: Python :: 3
Classifier: Programming Language :: Rust
Classifier: License :: OSI Approved :: Apache Software License
Requires-Dist: maturin>=1.5 ; extra == 'dev'
Requires-Dist: pytest>=7.0 ; extra == 'dev'
Provides-Extra: dev
License-File: LICENSE
Summary: Rust-backed Python library for reading and writing PPTX files.
Author: Slidex Contributors
License: Apache-2.0
Requires-Python: >=3.9
